kompress_cache/__init__.py
kompress_cache/cache.py
kompress_cache/config.py
kompress_cache/decorators.py
kompress_cache-0.1.2.dist-info/licenses/LICENSE
kompress_cache-0.1.2.dist-info/METADATA
kompress_cache-0.1.2.dist-info/WHEEL
kompress_cache-0.1.2.dist-info/top_level.txt
kompress_cache-0.1.2.dist-info/RECORD
