Metadata-Version: 2.4
Name: kompress_cache
Version: 0.1.2
Summary: A Redis-based cache that routes writes to the primary and reads from replicas with failover.
Author-email: Sudhir Ravindramohan <sudhir.ravindramohan@utvyakta.com>, Poovarasan <poovarasan.v@utvyakta.com>
Requires-Python: >=3.9
License-File: LICENSE
Requires-Dist: redis[hiredis]
Requires-Dist: pydantic
Requires-Dist: fastapi
Dynamic: license-file
